lmtoolbox/__init__.py
lmtoolbox/cli.py
lmtoolbox/video_summarization.py
lmtoolbox/tools/templates/cheermeup.yaml
lmtoolbox/tools/templates/codereview.yaml
lmtoolbox/tools/templates/commitgen.yaml
lmtoolbox/tools/templates/critique.yaml
lmtoolbox/tools/templates/define.yaml
lmtoolbox/tools/templates/explain.yaml
lmtoolbox/tools/templates/lessonize.yaml
lmtoolbox/tools/templates/life.yaml
lmtoolbox/tools/templates/pathlearner.yaml
lmtoolbox/tools/templates/proofread.yaml
lmtoolbox/tools/templates/study.yaml
lmtoolbox/tools/templates/summarize.yaml
lmtoolbox/tools/templates/teachlib.yaml
lmtoolbox/tools/templates/thesaurus.yaml
lmtoolbox/tools/templates/translate.yaml
lmtoolbox/tools/templates/video_summarization.yaml
lmtoolbox-0.5.19.dist-info/licenses/LICENSE
lmtoolbox-0.5.19.dist-info/METADATA
lmtoolbox-0.5.19.dist-info/WHEEL
lmtoolbox-0.5.19.dist-info/entry_points.txt
lmtoolbox-0.5.19.dist-info/top_level.txt
lmtoolbox-0.5.19.dist-info/RECORD
