Metadata-Version: 2.4
Name: LMtoolbox
Version: 0.5.19
Summary: A collection of CLI tools leveraging language models
Home-page: https://github.com/sderev/lmtoolbox
Author: Sébastien De Revière
License: Apache Licence, Version 2.0
Project-URL: Documentation, https://github.com/sderev/lmtoolbox
Project-URL: Issues, http://github.com/sderev/lmtoolbox/issues
Project-URL: Changelog, https://github.com/sderev/lmtoolbox/releases
Requires-Python: >=3.8
License-File: LICENSE
Requires-Dist: PyYAML
Requires-Dist: click
Requires-Dist: lmterminal==0.0.43
Requires-Dist: openai<1.0
Requires-Dist: rich
Requires-Dist: shellgenius==0.1.16
Requires-Dist: strip-tags
Requires-Dist: tiktoken
Requires-Dist: validators
Requires-Dist: vocabmaster==0.2.0
Requires-Dist: youtube-transcript-api==0.6.2
Dynamic: author
Dynamic: description
Dynamic: description-content-type
Dynamic: home-page
Dynamic: license
Dynamic: license-file
Dynamic: project-url
Dynamic: requires-dist
Dynamic: requires-python
Dynamic: summary
